modbus_scale_client/__init__.py
modbus_scale_client/modbus_scale_client.py
modbus_scale_client-1.1.3.dist-info/licenses/LICENSE.md
modbus_scale_client-1.1.3.dist-info/METADATA
modbus_scale_client-1.1.3.dist-info/WHEEL
modbus_scale_client-1.1.3.dist-info/top_level.txt
modbus_scale_client-1.1.3.dist-info/RECORD
