Metadata-Version: 2.4
Name: modbus-scale-client
Version: 1.1.3
Summary: Weigh scale Modbus Ethernet client
Author-email: Rodney Elliott <rodney.elliott@canterbury.ac.nz>
License-Expression: GPL-3.0-or-later
Project-URL: Homepage, https://gitlab.com/uc_mech_wing/robotics_control_lab/uc-02-2024/modbus_scale_client
Project-URL: Issues, https://gitlab.com/uc_mech_wing/robotics_control_lab/uc-02-2024/modbus_scale_client/-/issues
Keywords: Modbus,Raspberry Pi,Scale
Classifier: Environment :: Console
Classifier: Intended Audience :: Developers
Classifier: Intended Audience :: Education
Classifier: Operating System :: OS Independent
Classifier: Programming Language :: Python :: 3
Requires-Python: >=3.9
License-File: LICENSE.md
Requires-Dist: pyModbusTCP==0.2.1
Dynamic: license-file
